aoe2mapgenerator/Cpython/build/lib.linux-x86_64-3.8/knn.cpython-38-x86_64-linux-gnu.so
aoe2mapgenerator/Cpython/build/lib.win-amd64-cpython-310/factorial.cp310-win_amd64.pyd
aoe2mapgenerator/Cpython/build/lib.win-amd64-cpython-310/knn.cp310-win_amd64.pyd
aoe2mapgenerator/Cpython/build/temp.linux-x86_64-3.8/knn.o
aoe2mapgenerator/Cpython/build/temp.win-amd64-cpython-310/Release/factorial.cp310-win_amd64.exp
aoe2mapgenerator/Cpython/build/temp.win-amd64-cpython-310/Release/factorial.cp310-win_amd64.lib
aoe2mapgenerator/Cpython/build/temp.win-amd64-cpython-310/Release/factorial.obj
aoe2mapgenerator/Cpython/build/temp.win-amd64-cpython-310/Release/knn.cp310-win_amd64.exp
aoe2mapgenerator/Cpython/build/temp.win-amd64-cpython-310/Release/knn.cp310-win_amd64.lib
aoe2mapgenerator/Cpython/build/temp.win-amd64-cpython-310/Release/knn.obj
aoe2mapgenerator/Cpython/knn.c
aoe2mapgenerator/Cpython/knn.cp310-win_amd64.pyd
aoe2mapgenerator/Cpython/main.ipynb
aoe2mapgenerator/Cpython/setup.py
aoe2mapgenerator/GeneratorTest.ipynb
aoe2mapgenerator/__init__.py
aoe2mapgenerator/aoe2_map_generator.egg-info/.pypirc
aoe2mapgenerator/aoe2_map_generator.egg-info/PKG-INFO
aoe2mapgenerator/aoe2_map_generator.egg-info/SOURCES.txt
aoe2mapgenerator/aoe2_map_generator.egg-info/dependency_links.txt
aoe2mapgenerator/aoe2_map_generator.egg-info/top_level.txt
aoe2mapgenerator/aoe2mapgenerator.egg-info/PKG-INFO
aoe2mapgenerator/aoe2mapgenerator.egg-info/SOURCES.txt
aoe2mapgenerator/aoe2mapgenerator.egg-info/dependency_links.txt
aoe2mapgenerator/aoe2mapgenerator.egg-info/top_level.txt
aoe2mapgenerator/common/__init__.py
aoe2mapgenerator/common/constants/__init__.py
aoe2mapgenerator/common/constants/constants.py
aoe2mapgenerator/common/enums/__init__.py
aoe2mapgenerator/common/enums/enum.py
aoe2mapgenerator/docs/plans.txt
aoe2mapgenerator/maingenerator.ipynb
aoe2mapgenerator/maingenerator.py
aoe2mapgenerator/map/__init__.py
aoe2mapgenerator/map/map.py
aoe2mapgenerator/map/map_utils.py
aoe2mapgenerator/output.png
aoe2mapgenerator/scenario/__init__.py
aoe2mapgenerator/scenario/scenario.py
aoe2mapgenerator/scenario-file.ipynb
aoe2mapgenerator/templates/example_templates/city.yaml
aoe2mapgenerator/templates/example_templates/fortress.yaml
aoe2mapgenerator/templates/example_templates/oak_forest.yaml
aoe2mapgenerator/templates/example_templates/snow_forest.yaml
aoe2mapgenerator/templates/example_templates/temp.yaml
aoe2mapgenerator/templates/example_templates/walls.yaml
aoe2mapgenerator/terrain/terrain.py
aoe2mapgenerator-0.1.4.dist-info/METADATA
aoe2mapgenerator-0.1.4.dist-info/WHEEL
aoe2mapgenerator-0.1.4.dist-info/RECORD
