Metadata-Version: 2.1
Name: aoe2mapgenerator
Version: 0.1.4
Summary: Age of Empires II map generator
Author: QuantumCreation
Author-email: joseph6433@gmail.com
Requires-Python: >=3.8,<4.0
Classifier: Programming Language :: Python :: 3
Classifier: Programming Language :: Python :: 3.8
Classifier: Programming Language :: Python :: 3.9
Classifier: Programming Language :: Python :: 3.10
Classifier: Programming Language :: Python :: 3.11
Requires-Dist: AoE2ScenarioParser (>=0.1.56,<0.2.0)
